{
  "parent": "minecraft:recipes/root",
  "criteria": {
    "has_altar_stone_tiles": {
      "conditions": {
        "items": [
          {
            "items": "rubinated_nether:altar_stone_tiles"
          }
        ]
      },
      "trigger": "minecraft:inventory_changed"
    },
    "has_the_recipe": {
      "conditions": {
        "recipe": "rubinated_nether:altar_stone_tiles_wall"
      },
      "trigger": "minecraft:recipe_unlocked"
    }
  },
  "requirements": [
    [
      "has_the_recipe",
      "has_altar_stone_tiles"
    ]
  ],
  "rewards": {
    "recipes": [
      "rubinated_nether:altar_stone_tiles_wall"
    ]
  }
}